langextract_docling/__init__.py
langextract_docling/markdown_chunker.py
langextract_docling-1.0.9a1.dist-info/licenses/LICENSE
langextract_docling-1.0.9a1.dist-info/METADATA
langextract_docling-1.0.9a1.dist-info/WHEEL
langextract_docling-1.0.9a1.dist-info/top_level.txt
langextract_docling-1.0.9a1.dist-info/RECORD
